git_patch/__init__.py
git_patch/git_patch.py
git_patch-2.0.1.dist-info/DESCRIPTION.rst
git_patch-2.0.1.dist-info/entry_points.txt
git_patch-2.0.1.dist-info/METADATA
git_patch-2.0.1.dist-info/metadata.json
git_patch-2.0.1.dist-info/RECORD
git_patch-2.0.1.dist-info/top_level.txt
git_patch-2.0.1.dist-info/WHEEL
