Metadata-Version: 2.0
Name: git-patch
Version: 2.0.1
Summary: Patch management for open source fork projects
Home-page: UNKNOWN
Author: Rajat Venkatesh
Author-email: rajatvenkatesh@alumni.cmu.edu
License: Apache 2.0
Platform: UNKNOWN
Classifier: Development Status :: 4 - Beta
Classifier: Intended Audience :: Developers
Classifier: Topic :: Software Development :: Build Tools
Classifier: Programming Language :: Python :: 2
Classifier: Programming Language :: Python :: 2.6
Classifier: Programming Language :: Python :: 2.7
Requires-Dist: pyaml
Requires-Dist: argparse
